<annotation>
	<folder>train</folder>
	<filename>22990246-right-turn-sign-a-sign-warns-of-a-sharp-right-turn-2.jpg</filename>
	<path>C:\Users\Woradej\Desktop\train\22990246-right-turn-sign-a-sign-warns-of-a-sharp-right-turn-2.jpg</path>
	<source>
		<database>Unknown</database>
	</source>
	<size>
		<width>1300</width>
		<height>866</height>
		<depth>3</depth>
	</size>
	<segmented>0</segmented>
	<object>
		<name>right</name>
		<pose>Unspecified</pose>
		<truncated>0</truncated>
		<difficult>0</difficult>
		<bndbox>
			<xmin>124</xmin>
			<ymin>69</ymin>
			<xmax>480</xmax>
			<ymax>425</ymax>
		</bndbox>
	</object>
</annotation>
